<?xml version="1.0" encoding="UTF-8"?>
<billStatus>
  <bill>
    <titles>
      <item>
        <chamberName />
        <title>Condemning anti-Semitism as hateful expressions of intolerance that are contradictory to the values and aspirations that define the people of the United States and condemning anti-Muslim discrimination and bigotry against minorities as hateful expressions of intolerance that are contrary to the values and aspirations of the United States.</title>
        <titleType>Official Title as Introduced</titleType>
        <chamberCode />
        <parentTitleType />
      </item>
      <item>
        <chamberName />
        <title>Condemning anti-Semitism as hateful expressions of intolerance that are contradictory to the values and aspirations that define the people of the United States and condemning anti-Muslim discrimination and bigotry against minorities as hateful expressions of intolerance that are contrary to the values and aspirations of the United States.</title>
        <titleType>Display Title</titleType>
        <chamberCode />
        <parentTitleType />
      </item>
    </titles>
    <billNumber>183</billNumber>
    <sponsors>
      <item>
        <fullName>Rep. Raskin, Jamie [D-MD-8]</fullName>
        <party>D</party>
        <byRequestType />
        <lastName>Raskin</lastName>
        <middleName />
        <state>MD</state>
        <bioguideId>R000606</bioguideId>
        <identifiers>
          <bioguideId>R000606</bioguideId>
          <gpoId />
          <lisID>2332</lisID>
        </identifiers>
        <district>8</district>
        <firstName>Jamie</firstName>
      </item>
    </sponsors>
    <committeeReports />
    <cboCostEstimates />
    <cosponsors>
      <item>
        <firstName>Cedric</firstName>
        <middleName>L.</middleName>
        <sponsorshipDate>2019-03-07</sponsorshipDate>
        <identifiers>
          <lisID>2023</lisID>
          <bioguideId>R000588</bioguideId>
          <gpoId>7960</gpoId>
        </identifiers>
        <district>2</district>
        <party>D</party>
        <isOriginalCosponsor>True</isOriginalCosponsor>
        <fullName>Rep. Richmond, Cedric L. [D-LA-2]</fullName>
        <state>LA</state>
        <bioguideId>R000588</bioguideId>
        <lastName>Richmond</lastName>
        <sponsorshipWithdrawnDate />
      </item>
    </cosponsors>
    <title>Condemning anti-Semitism as hateful expressions of intolerance that are contradictory to the values and aspirations that define the people of the United States and condemning anti-Muslim discrimination and bigotry against minorities as hateful expressions of intolerance that are contrary to the values and aspirations of the United States.</title>
    <summaries>
      <billSummaries>
        <item>
          <updateDate>2019-03-07T05:00:00Z</updateDate>
          <lastSummaryUpdateDate>2019-03-11T14:51:57Z</lastSummaryUpdateDate>
          <text><![CDATA[<p>This resolution rejects the perpetuation of anti-Semitic stereotypes in the United States and around the world, and condemns anti-Semitic acts and statements. The resolution reaffirms support for the mandate of the United States Special Envoy to Monitor and Combat Anti-Semitism. Additionally, the resolution rejects attempts to justify hatred or violent attacks over political frustrations. Law enforcement is encouraged to avoid conduct that raises the specter of unconstitutional profiling against anyone because of their race, religion, nationality, politics, or social group.</p> <p>This resolution also acknowledges the harm suffered by Muslims from harassment, discrimination, and violence and condemns anti-Muslim discrimination and bigotry against all minorities.</p> <p>Finally, the resolution condemns death threats received by Jewish and Muslim Members of Congress.</p>]]></text>
          <actionDesc>Introduced in House</actionDesc>
          <actionDate>2019-03-07</actionDate>
          <versionCode>00</versionCode>
          <name>Introduced in House</name>
        </item>
        <item>
          <updateDate>2019-03-07T14:21:49Z</updateDate>
          <lastSummaryUpdateDate>2019-03-11T21:19:05Z</lastSummaryUpdateDate>
          <text><![CDATA[<p>This resolution rejects the perpetuation of anti-Semitic stereotypes in the United States and around the world, and condemns anti-Semitic acts and statements. The resolution reaffirms support for the mandate of the United States Special Envoy to Monitor and Combat Anti-Semitism. Additionally, the resolution rejects attempts to justify hatred or violent attacks over political frustrations. Law enforcement is encouraged to avoid conduct that raises the specter of unconstitutional profiling against anyone because of their race, religion, nationality, politics, or social group.</p> <p>This resolution also acknowledges the harm suffered by Muslims from harassment, discrimination, and violence and condemns anti-Muslim discrimination and bigotry against all minorities.</p> <p>Finally, the resolution condemns death threats received by Jewish and Muslim Members of Congress.</p>]]></text>
          <actionDesc>Passed House</actionDesc>
          <actionDate>2019-03-07</actionDate>
          <versionCode>53</versionCode>
          <name>Passed House</name>
        </item>
      </billSummaries>
    </summaries>
    <calendarNumbers />
    <originChamber>House</originChamber>
    <updateDate>2019-07-30T13:00:03Z</updateDate>
    <constitutionalAuthorityStatementText />
    <recordedVotes>
      <recordedVote>
        <url>http://clerk.house.gov/evs/2019/roll108.xml</url>
        <sessionNumber>1</sessionNumber>
        <fullActionName>Final Passage Under Suspension of the Rules Results</fullActionName>
        <rollNumber>108</rollNumber>
        <date>2019-03-07T22:34:25Z</date>
        <chamber>House</chamber>
        <congress>116</congress>
      </recordedVote>
    </recordedVotes>
    <subjects>
      <billSubjects>
        <legislativeSubjects>
          <item>
            <name>Arab-Israeli relations</name>
          </item>
          <item>
            <name>Assault and harassment offenses</name>
          </item>
          <item>
            <name>Due process and equal protection</name>
          </item>
          <item>
            <name>Hate crimes</name>
          </item>
          <item>
            <name>Human rights</name>
          </item>
          <item>
            <name>Israel</name>
          </item>
          <item>
            <name>Law enforcement administration and funding</name>
          </item>
          <item>
            <name>Members of Congress</name>
          </item>
          <item>
            <name>Middle East</name>
          </item>
          <item>
            <name>Protection of officials</name>
          </item>
          <item>
            <name>Racial and ethnic relations</name>
          </item>
          <item>
            <name>Religion</name>
          </item>
          <item>
            <name>Violent crime</name>
          </item>
        </legislativeSubjects>
        <policyArea>
          <name>Civil Rights and Liberties, Minority Issues</name>
        </policyArea>
      </billSubjects>
    </subjects>
    <createDate>2019-03-08T08:12:06Z</createDate>
    <version>1.0.0</version>
    <policyArea>
      <name>Civil Rights and Liberties, Minority Issues</name>
    </policyArea>
    <billType>HRES</billType>
    <laws />
    <notes />
    <actions>
      <actionTypeCounts>
        <finalPassageUnderSuspensionOfTheRulesResults>1</finalPassageUnderSuspensionOfTheRulesResults>
        <billReferrals>2</billReferrals>
        <considerationByHouse>1</considerationByHouse>
        <motionToReconsiderResults>1</motionToReconsiderResults>
        <introducedInTheHouse>1</introducedInTheHouse>
        <introducedInHouse>1</introducedInHouse>
        <motionMadeToSuspendTheRules>1</motionMadeToSuspendTheRules>
        <generalDebate>1</generalDebate>
        <passedAgreedToInHouse>1</passedAgreedToInHouse>
      </actionTypeCounts>
      <item>
        <actionCode>H38310</actionCode>
        <text>Motion to reconsider laid on the table Agreed to without objection.</text>
        <type>Floor</type>
        <actionDate>2019-03-07</actionDate>
        <links />
        <committee />
        <actionTime>17:34:31</actionTime>
        <sourceSystem>
          <name>House floor actions</name>
          <code>2</code>
        </sourceSystem>
      </item>
      <item>
        <actionCode>H37300</actionCode>
        <text>On motion to suspend the rules and agree to the resolution, as amended Agreed to by the Yeas and Nays: (2/3 required): 407 - 23, 1 Present (Roll no. 108). (text: CR H2547-2548)</text>
        <type>Floor</type>
        <actionDate>2019-03-07</actionDate>
        <links>
          <link>
            <name>H2547-2548</name>
            <url>https://www.congress.gov/congressional-record/volume-165/house-section/page/H2547-2548</url>
          </link>
          <link>
            <name>Roll no. 108</name>
            <url>http://clerk.house.gov/evs/2019/roll108.xml</url>
          </link>
        </links>
        <committee />
        <actionTime>17:34:25</actionTime>
        <sourceSystem>
          <name>House floor actions</name>
          <code>2</code>
        </sourceSystem>
      </item>
      <item>
        <actionCode>8000</actionCode>
        <text>Passed/agreed to in House: On motion to suspend the rules and agree to the resolution, as amended Agreed to by the Yeas and Nays: (2/3 required): 407 - 23, 1 Present (Roll no. 108).(text: CR H2547-2548)</text>
        <type>Floor</type>
        <actionDate>2019-03-07</actionDate>
        <links>
          <link>
            <name>H2547-2548</name>
            <url>https://www.congress.gov/congressional-record/volume-165/house-section/page/H2547-2548</url>
          </link>
          <link>
            <name>Roll no. 108</name>
            <url>http://clerk.house.gov/evs/2019/roll108.xml</url>
          </link>
        </links>
        <committee />
        <actionTime>17:34:25</actionTime>
        <sourceSystem>
          <name>Library of Congress</name>
          <code>9</code>
        </sourceSystem>
      </item>
      <item>
        <actionCode>H8D000</actionCode>
        <text>DEBATE - The House proceeded with forty minutes of debate on H. Res. 183.</text>
        <type>Floor</type>
        <actionDate>2019-03-07</actionDate>
        <links>
          <link>
            <name>H. Res. 183</name>
            <url>https://www.congress.gov/bill/116th-congress/house-resolution/183</url>
          </link>
        </links>
        <committee />
        <actionTime>16:02:28</actionTime>
        <sourceSystem>
          <name>House floor actions</name>
          <code>2</code>
        </sourceSystem>
      </item>
      <item>
        <actionCode>H30000</actionCode>
        <text>Considered under suspension of the rules. (consideration: CR H2547-2555)</text>
        <type>Floor</type>
        <actionDate>2019-03-07</actionDate>
        <links>
          <link>
            <name>H2547-2555</name>
            <url>https://www.congress.gov/congressional-record/volume-165/house-section/page/H2547-2555</url>
          </link>
        </links>
        <committee />
        <actionTime>16:02:26</actionTime>
        <sourceSystem>
          <name>House floor actions</name>
          <code>2</code>
        </sourceSystem>
      </item>
      <item>
        <actionCode>H30300</actionCode>
        <text>Mr. Nadler moved to suspend the rules and agree to the resolution, as amended.</text>
        <type>Floor</type>
        <actionDate>2019-03-07</actionDate>
        <links />
        <committee />
        <actionTime>16:02:11</actionTime>
        <sourceSystem>
          <name>House floor actions</name>
          <code>2</code>
        </sourceSystem>
      </item>
      <item>
        <actionCode>H11100</actionCode>
        <text>Referred to the Committee on the Judiciary, and in addition to the Committee on Foreign Affairs, for a period to be subsequently determined by the Speaker, in each case for consideration of such provisions as fall within the jurisdiction of the committee concerned.</text>
        <sourceSystem>
          <name>House floor actions</name>
          <code>2</code>
        </sourceSystem>
        <links />
        <committee>
          <name>Foreign Affairs Committee</name>
          <systemCode>hsfa00</systemCode>
        </committee>
        <actionDate>2019-03-07</actionDate>
        <type>IntroReferral</type>
      </item>
      <item>
        <actionCode>H11100</actionCode>
        <text>Referred to the Committee on the Judiciary, and in addition to the Committee on Foreign Affairs, for a period to be subsequently determined by the Speaker, in each case for consideration of such provisions as fall within the jurisdiction of the committee concerned.</text>
        <sourceSystem>
          <name>House floor actions</name>
          <code>2</code>
        </sourceSystem>
        <links />
        <committee>
          <name>Judiciary Committee</name>
          <systemCode>hsju00</systemCode>
        </committee>
        <actionDate>2019-03-07</actionDate>
        <type>IntroReferral</type>
      </item>
      <item>
        <actionCode>Intro-H</actionCode>
        <text>Introduced in House</text>
        <type>IntroReferral</type>
        <actionDate>2019-03-07</actionDate>
        <committee />
        <links />
        <sourceSystem>
          <name>Library of Congress</name>
          <code>9</code>
        </sourceSystem>
      </item>
      <item>
        <actionCode>1000</actionCode>
        <text>Introduced in House</text>
        <type>IntroReferral</type>
        <actionDate>2019-03-07</actionDate>
        <committee />
        <links />
        <sourceSystem>
          <name>Library of Congress</name>
          <code>9</code>
        </sourceSystem>
      </item>
      <actionByCounts>
        <houseOfRepresentatives>10</houseOfRepresentatives>
      </actionByCounts>
    </actions>
    <committees>
      <billCommittees>
        <item>
          <chamber>House</chamber>
          <systemCode>hsfa00</systemCode>
          <name>Foreign Affairs Committee</name>
          <activities>
            <item>
              <name>Referred to</name>
              <date>2019-03-07T15:01:35Z</date>
            </item>
          </activities>
          <type>Standing</type>
          <subcommittees />
        </item>
        <item>
          <chamber>House</chamber>
          <systemCode>hsju00</systemCode>
          <name>Judiciary Committee</name>
          <activities>
            <item>
              <name>Referred to</name>
              <date>2019-03-07T15:01:30Z</date>
            </item>
          </activities>
          <type>Standing</type>
          <subcommittees />
        </item>
      </billCommittees>
    </committees>
    <relatedBills />
    <latestAction>
      <text>Motion to reconsider laid on the table Agreed to without objection.</text>
      <actionDate>2019-03-07</actionDate>
      <links />
      <actionTime>17:34:31</actionTime>
    </latestAction>
    <amendments />
    <textVersions>
      <item>
        <date>2019-03-07T05:00:00Z</date>
        <formats>
          <item>
            <url>https://www.govinfo.gov/content/pkg/BILLS-116hres183ih/xml/BILLS-116hres183ih.xml</url>
          </item>
        </formats>
        <type>Introduced in House</type>
      </item>
      <item>
        <date>2019-03-07T05:00:00Z</date>
        <formats>
          <item>
            <url>https://www.govinfo.gov/content/pkg/BILLS-116hres183eh/xml/BILLS-116hres183eh.xml</url>
          </item>
        </formats>
        <type>Engrossed in House</type>
      </item>
    </textVersions>
    <introducedDate>2019-03-07</introducedDate>
    <congress>116</congress>
  </bill>
  <dublinCore xmlns:dc="http://purl.org/dc/elements/1.1/">
    <dc:format>text/xml</dc:format>
    <dc:language>EN</dc:language>
    <dc:rights>Pursuant to Title 17 Section 105 of the United States Code, this file is not subject to copyright protection and is in the public domain.</dc:rights>
    <dc:contributor>Congressional Research Service, Library of Congress</dc:contributor>
    <dc:description>This file contains bill summaries and statuses for federal legislation. A bill summary describes the most significant provisions of a piece of legislation and details the effects the legislative text may have on current law and federal programs. Bill summaries are authored by the Congressional Research Service (CRS) of the Library of Congress. As stated in Public Law 91-510 (2 USC 166 (d)(6)), one of the duties of CRS is "to prepare summaries and digests of bills and resolutions of a public general nature introduced in the Senate or House of Representatives". For more information, refer to the User Guide that accompanies this file.</dc:description>
  </dublinCore>
</billStatus>

