{
  "actions": [
    {
      "acted_at": "2019-06-25", 
      "action_code": "10000", 
      "references": [], 
      "text": "Introduced in Senate", 
      "type": "action"
    }, 
    {
      "acted_at": "2019-06-25", 
      "action_code": "", 
      "committees": [
        "SSBK"
      ], 
      "references": [], 
      "status": "REFERRED", 
      "text": "Read twice and referred to the Committee on Banking, Housing, and Urban Affairs.", 
      "type": "referral"
    }, 
    {
      "acted_at": "2019-10-24", 
      "action_code": "", 
      "committee": "Committee on Banking, Housing, and Urban Affairs", 
      "committees": [
        "SSBK"
      ], 
      "references": [], 
      "text": "Committee on Banking, Housing, and Urban Affairs. Hearings held.", 
      "type": "hearings"
    }
  ], 
  "amendments": [], 
  "bill_id": "s1951-116", 
  "bill_type": "s", 
  "by_request": false, 
  "committee_reports": [], 
  "committees": [
    {
      "activity": [
        "hearings", 
        "referral"
      ], 
      "committee": "Senate Banking, Housing, and Urban Affairs", 
      "committee_id": "SSBK"
    }
  ], 
  "congress": "116", 
  "cosponsors": [
    {
      "bioguide_id": "H001089", 
      "district": null, 
      "name": "Hawley, Josh", 
      "original_cosponsor": true, 
      "sponsored_at": "2019-06-25", 
      "state": "MO", 
      "title": "Sen", 
      "withdrawn_at": null
    }
  ], 
  "enacted_as": null, 
  "history": {
    "active": true, 
    "active_at": "2019-10-24", 
    "awaiting_signature": false, 
    "enacted": false, 
    "vetoed": false
  }, 
  "introduced_at": "2019-06-25", 
  "number": "1951", 
  "official_title": "A bill to require the Securities and Exchange Commission to promulgate regulations relating to the disclosure of certain commercial data, and for other purposes.", 
  "popular_title": null, 
  "related_bills": [], 
  "short_title": "Designing Accounting Safeguards To Help Broaden Oversight and Regulations on Data", 
  "sponsor": {
    "bioguide_id": "W000805", 
    "district": null, 
    "name": "Warner, Mark R.", 
    "state": "VA", 
    "title": "Sen", 
    "type": "person"
  }, 
  "status": "REFERRED", 
  "status_at": "2019-06-25", 
  "subjects": [
    "Finance and financial sector"
  ], 
  "subjects_top_term": "Finance and financial sector", 
  "summary": null, 
  "titles": [
    {
      "as": "introduced", 
      "is_for_portion": false, 
      "title": "A bill to require the Securities and Exchange Commission to promulgate regulations relating to the disclosure of certain commercial data, and for other purposes.", 
      "type": "official"
    }, 
    {
      "as": "introduced", 
      "is_for_portion": false, 
      "title": "Designing Accounting Safeguards To Help Broaden Oversight and Regulations on Data", 
      "type": "short"
    }, 
    {
      "as": "introduced", 
      "is_for_portion": false, 
      "title": "Designing Accounting Safeguards To Help Broaden Oversight and Regulations on Data", 
      "type": "short"
    }, 
    {
      "as": null, 
      "is_for_portion": false, 
      "title": "Designing Accounting Safeguards To Help Broaden Oversight and Regulations on Data", 
      "type": "display"
    }
  ], 
  "updated_at": "2019-10-25T04:51:20Z", 
  "url": "https://www.govinfo.gov/bulkdata/BILLSTATUS/116/s/BILLSTATUS-116s1951.xml"
}