<?xml version="1.0" encoding="UTF-8"?>
<billStatus>
  <bill>
    <subjects>
      <billSubjects>
        <legislativeSubjects />
        <policyArea>
          <name>Health</name>
        </policyArea>
      </billSubjects>
    </subjects>
    <title>To amend the Public Health Service Act to reauthorize Johanna's Law, and for other purposes.</title>
    <laws />
    <introducedDate>2019-09-27</introducedDate>
    <latestAction>
      <links />
      <text>Referred to the House Committee on Energy and Commerce.</text>
      <actionDate>2019-09-27</actionDate>
    </latestAction>
    <titles>
      <item>
        <title>To amend the Public Health Service Act to reauthorize Johanna's Law, and for other purposes.</title>
        <chamberCode />
        <titleType>Official Title as Introduced</titleType>
        <chamberName />
        <parentTitleType />
      </item>
      <item>
        <title>To amend the Public Health Service Act to reauthorize Johanna's Law, and for other purposes.</title>
        <chamberCode />
        <titleType>Display Title</titleType>
        <chamberName />
        <parentTitleType />
      </item>
    </titles>
    <congress>116</congress>
    <cboCostEstimates />
    <sponsors>
      <item>
        <bioguideId>D000216</bioguideId>
        <lastName>DELAURO</lastName>
        <byRequestType />
        <fullName>Rep. DeLauro, Rosa L. [D-CT-3]</fullName>
        <district>3</district>
        <firstName>ROSA</firstName>
        <identifiers>
          <gpoId>7868</gpoId>
          <lisID>281</lisID>
          <bioguideId>D000216</bioguideId>
        </identifiers>
        <middleName />
        <state>CT</state>
        <party>D</party>
      </item>
    </sponsors>
    <billType>HR</billType>
    <textVersions>
      <item>
        <formats>
          <item>
            <url>https://www.govinfo.gov/content/pkg/BILLS-116hr4560ih/xml/BILLS-116hr4560ih.xml</url>
          </item>
        </formats>
        <type>Introduced in House</type>
        <date>2019-09-27T04:00:00Z</date>
      </item>
    </textVersions>
    <actions>
      <actionTypeCounts>
        <introducedInHouse>1</introducedInHouse>
        <introducedInTheHouse>1</introducedInTheHouse>
        <billReferrals>1</billReferrals>
      </actionTypeCounts>
      <item>
        <actionDate>2019-09-27</actionDate>
        <sourceSystem>
          <code>2</code>
          <name>House floor actions</name>
        </sourceSystem>
        <text>Referred to the House Committee on Energy and Commerce.</text>
        <type>IntroReferral</type>
        <committee>
          <systemCode>hsif00</systemCode>
          <name>Energy and Commerce Committee</name>
        </committee>
        <links />
        <actionCode>H11100</actionCode>
      </item>
      <item>
        <links />
        <actionDate>2019-09-27</actionDate>
        <text>Introduced in House</text>
        <type>IntroReferral</type>
        <committee />
        <sourceSystem>
          <code>9</code>
          <name>Library of Congress</name>
        </sourceSystem>
        <actionCode>Intro-H</actionCode>
      </item>
      <item>
        <links />
        <actionDate>2019-09-27</actionDate>
        <text>Introduced in House</text>
        <type>IntroReferral</type>
        <committee />
        <sourceSystem>
          <code>9</code>
          <name>Library of Congress</name>
        </sourceSystem>
        <actionCode>1000</actionCode>
      </item>
      <actionByCounts>
        <houseOfRepresentatives>3</houseOfRepresentatives>
      </actionByCounts>
    </actions>
    <policyArea>
      <name>Health</name>
    </policyArea>
    <calendarNumbers />
    <version>1.0.0</version>
    <notes />
    <summaries>
      <billSummaries />
    </summaries>
    <billNumber>4560</billNumber>
    <recordedVotes />
    <cosponsors>
      <item>
        <bioguideId>F000466</bioguideId>
        <identifiers>
          <bioguideId>F000466</bioguideId>
          <lisID>2345</lisID>
          <gpoId />
        </identifiers>
        <lastName>Fitzpatrick</lastName>
        <fullName>Rep. Fitzpatrick, Brian K. [R-PA-1]</fullName>
        <state>PA</state>
        <party>R</party>
        <sponsorshipWithdrawnDate />
        <sponsorshipDate>2019-09-27</sponsorshipDate>
        <district>1</district>
        <firstName>Brian</firstName>
        <isOriginalCosponsor>True</isOriginalCosponsor>
        <middleName>K.</middleName>
      </item>
      <item>
        <bioguideId>N000002</bioguideId>
        <identifiers>
          <bioguideId>N000002</bioguideId>
          <gpoId>8069</gpoId>
          <lisID>850</lisID>
        </identifiers>
        <lastName>NADLER</lastName>
        <fullName>Rep. Nadler, Jerrold [D-NY-10]</fullName>
        <state>NY</state>
        <party>D</party>
        <sponsorshipWithdrawnDate />
        <sponsorshipDate>2019-09-27</sponsorshipDate>
        <district>10</district>
        <firstName>JERROLD</firstName>
        <isOriginalCosponsor>True</isOriginalCosponsor>
        <middleName />
      </item>
      <item>
        <bioguideId>D000624</bioguideId>
        <identifiers>
          <bioguideId>D000624</bioguideId>
          <lisID>2251</lisID>
          <gpoId />
        </identifiers>
        <lastName>Dingell</lastName>
        <fullName>Rep. Dingell, Debbie [D-MI-12]</fullName>
        <state>MI</state>
        <party>D</party>
        <sponsorshipWithdrawnDate />
        <sponsorshipDate>2019-09-27</sponsorshipDate>
        <district>12</district>
        <firstName>Debbie</firstName>
        <isOriginalCosponsor>True</isOriginalCosponsor>
        <middleName />
      </item>
      <item>
        <bioguideId>B001285</bioguideId>
        <identifiers>
          <bioguideId>B001285</bioguideId>
          <gpoId />
          <lisID>2106</lisID>
        </identifiers>
        <lastName>Brownley</lastName>
        <fullName>Rep. Brownley, Julia [D-CA-26]</fullName>
        <state>CA</state>
        <party>D</party>
        <sponsorshipWithdrawnDate />
        <sponsorshipDate>2019-10-08</sponsorshipDate>
        <district>26</district>
        <firstName>Julia</firstName>
        <isOriginalCosponsor>False</isOriginalCosponsor>
        <middleName />
      </item>
      <item>
        <bioguideId>C001055</bioguideId>
        <identifiers>
          <bioguideId>C001055</bioguideId>
          <lisID>1693</lisID>
          <gpoId />
        </identifiers>
        <lastName>Case</lastName>
        <fullName>Rep. Case, Ed [D-HI-1]</fullName>
        <state>HI</state>
        <party>D</party>
        <sponsorshipWithdrawnDate />
        <sponsorshipDate>2019-10-16</sponsorshipDate>
        <district>1</district>
        <firstName>Ed</firstName>
        <isOriginalCosponsor>False</isOriginalCosponsor>
        <middleName />
      </item>
      <item>
        <bioguideId>V000132</bioguideId>
        <identifiers>
          <bioguideId>V000132</bioguideId>
          <gpoId />
          <lisID>2167</lisID>
        </identifiers>
        <lastName>Vela</lastName>
        <fullName>Rep. Vela, Filemon [D-TX-34]</fullName>
        <state>TX</state>
        <party>D</party>
        <sponsorshipWithdrawnDate />
        <sponsorshipDate>2019-10-21</sponsorshipDate>
        <district>34</district>
        <firstName>Filemon</firstName>
        <isOriginalCosponsor>False</isOriginalCosponsor>
        <middleName />
      </item>
      <item>
        <bioguideId>P000607</bioguideId>
        <identifiers>
          <bioguideId>P000607</bioguideId>
          <gpoId />
          <lisID>2171</lisID>
        </identifiers>
        <lastName>Pocan</lastName>
        <fullName>Rep. Pocan, Mark [D-WI-2]</fullName>
        <state>WI</state>
        <party>D</party>
        <sponsorshipWithdrawnDate />
        <sponsorshipDate>2019-10-21</sponsorshipDate>
        <district>2</district>
        <firstName>Mark</firstName>
        <isOriginalCosponsor>False</isOriginalCosponsor>
        <middleName />
      </item>
      <item>
        <bioguideId>J000032</bioguideId>
        <identifiers>
          <bioguideId>J000032</bioguideId>
          <lisID>588</lisID>
          <gpoId>8174</gpoId>
        </identifiers>
        <lastName>JACKSON LEE</lastName>
        <fullName>Rep. Jackson Lee, Sheila [D-TX-18]</fullName>
        <state>TX</state>
        <party>D</party>
        <sponsorshipWithdrawnDate />
        <sponsorshipDate>2019-10-23</sponsorshipDate>
        <district>18</district>
        <firstName>SHEILA</firstName>
        <isOriginalCosponsor>False</isOriginalCosponsor>
        <middleName />
      </item>
    </cosponsors>
    <committees>
      <billCommittees>
        <item>
          <subcommittees />
          <systemCode>hsif00</systemCode>
          <type>Standing</type>
          <activities>
            <item>
              <name>Referred to</name>
              <date>2019-09-27T13:02:25Z</date>
            </item>
          </activities>
          <name>Energy and Commerce Committee</name>
          <chamber>House</chamber>
        </item>
      </billCommittees>
    </committees>
    <committeeReports />
    <amendments />
    <createDate>2019-09-28T07:12:23Z</createDate>
    <constitutionalAuthorityStatementText><![CDATA[<pre>[Congressional Record Volume 165, Number 157 (Friday, September 27, 2019)][House]From the Congressional Record Online through the Government Publishing Office [<a href="http://www.gpo.gov">www.gpo.gov</a>]By Ms. DeLAURO:H.R. 4560.Congress has the power to enact this legislation pursuantto the following:Article I, Section 8.[Page H8082]</pre>]]></constitutionalAuthorityStatementText>
    <updateDate>2019-10-24T07:42:22Z</updateDate>
    <originChamber>House</originChamber>
    <relatedBills />
  </bill>
  <dublinCore xmlns:dc="http://purl.org/dc/elements/1.1/">
    <dc:format>text/xml</dc:format>
    <dc:language>EN</dc:language>
    <dc:rights>Pursuant to Title 17 Section 105 of the United States Code, this file is not subject to copyright protection and is in the public domain.</dc:rights>
    <dc:contributor>Congressional Research Service, Library of Congress</dc:contributor>
    <dc:description>This file contains bill summaries and statuses for federal legislation. A bill summary describes the most significant provisions of a piece of legislation and details the effects the legislative text may have on current law and federal programs. Bill summaries are authored by the Congressional Research Service (CRS) of the Library of Congress. As stated in Public Law 91-510 (2 USC 166 (d)(6)), one of the duties of CRS is "to prepare summaries and digests of bills and resolutions of a public general nature introduced in the Senate or House of Representatives". For more information, refer to the User Guide that accompanies this file.</dc:description>
  </dublinCore>
</billStatus>

